{
	"tradedate" : "2015/03/02",
	"exchangecode" : "ODE",
	"timestamp" : "2015/3/2 12:35",
	"colsize" : 6,
	"rowsize" : 2,
	"months" : ["15/03", "15/05", "15/07", "15/09", "15/11", "16/01"],
	"prevprices" : ["169.6", "169.6", "169.6", "169.6", "169.6", "169.6"],
	"prevvolume" : "12",
	"amsize" : 1,
	"pmsize" : 1,
	"prices" : [
{
	"sid" : "12",
	"values" : ["169.6", "169.6", "169.6", "169.6", "169.6", "169.6"],
	"summary" : "6"
},
{
	"sid" : "22",
	"values" : ["", "", "", "", "", ""],
	"summary" : ""
}
],
	"durations" : ["0", "0", "0", "0", "0", "0"],
	"volumes" : ["1", "1", "1", "1", "1", "1"],
	"volumeall" : "6",
	"openints" : ["", "", "", "", "", ""],
	"openintall" : "0",
	"limits" : ["", "5.0", "5.0", "5.0", "5.0", "5.0"]
}